{
    "identifiers": {
        "anidb": "11878",
        "tvdb": "306407"
    },
    "names": [
        "Love Live! Sunshine!!"
    ],
    "parameters": {
        "default_season": "1"
    },
    "seasons": {
        "0": {
            "episodes": {
                "1": {
                    "mappings": [
                        {
                            "number": "0"
                        }
                    ]
                },
                "2": {
                    "mappings": [
                        {
                            "number": "0"
                        }
                    ]
                },
                "3": {
                    "mappings": [
                        {
                            "number": "0"
                        }
                    ]
                },
                "4": {
                    "mappings": [
                        {
                            "number": "0"
                        }
                    ]
                },
                "5": {
                    "mappings": [
                        {
                            "number": "0"
                        }
                    ]
                },
                "6": {
                    "mappings": [
                        {
                            "number": "0"
                        }
                    ]
                }
            }
        }
    }
}